{"name":"busqueda de apartamento en prishtina kosovo polje con precio menor de un millon","id":"buscar-en-el-mapa-y-tomar-foto-del-departamento;busqueda-de-apartamento-en-prishtina-kosovo-polje-con-precio-menor-de-un-millon","testSteps":[{"number":1,"description":"Given se debe realizar una busqueda de departamento","duration":19833,"startTime":"2019-10-01T10:55:29.700-05:00[America/Bogota]","screenshots":[{"screenshot":"7723cc58128e2e4c37af16ebaeb8f4c4f407d8284514f3623756201187169240.png","timeStamp":1569945349533}],"result":"SUCCESS","precondition":false,"level":0,"children":[{"number":2,"description":"Entrar","duration":19273,"startTime":"2019-10-01T10:55:30.254-05:00[America/Bogota]","screenshots":[{"screenshot":"7723cc58128e2e4c37af16ebaeb8f4c4f407d8284514f3623756201187169240.png","timeStamp":1569945349526}],"result":"SUCCESS","precondition":false,"level":1}]},{"number":3,"description":"When escojo las condiciones de departamento","duration":3,"startTime":"2019-10-01T10:55:49.534-05:00[America/Bogota]","screenshots":[{"screenshot":"7723cc58128e2e4c37af16ebaeb8f4c4f407d8284514f3623756201187169240.png","timeStamp":1569945349537}],"result":"SUCCESS","precondition":false,"level":0},{"number":4,"description":"Then busco en el mapa y hago el reporte","duration":3,"startTime":"2019-10-01T10:55:49.538-05:00[America/Bogota]","screenshots":[{"screenshot":"7723cc58128e2e4c37af16ebaeb8f4c4f407d8284514f3623756201187169240.png","timeStamp":1569945349541}],"result":"SUCCESS","precondition":false,"level":0}],"userStory":{"id":"buscar-en-el-mapa-y-tomar-foto-del-departamento","storyName":"Buscar en el mapa y tomar foto del departamento","path":"src/test/resources/features/Carlos.feature","type":"feature"},"featureTag":{"name":"Features/Buscar en el mapa y tomar foto del departamento","type":"feature"},"title":"busqueda de apartamento en prishtina kosovo polje con precio menor de un millon","tags":[{"name":"Mapa","type":"tag"},{"name":"Buscar en el mapa y tomar foto del departamento","type":"feature"}],"startTime":"2019-10-01T10:55:29.288-05:00[America/Bogota]","duration":20256,"projectKey":"","sessionId":"348bc41d3b146337e5fc8a3cadbe2d98","driver":"chrome","manual":false,"testSource":"Cucumber","result":"SUCCESS"}